ka_uts_cfg/__init__.py
ka_uts_cfg/__version__.py
ka_uts_cfg/do.py
ka_uts_cfg/parms.py
ka_uts_cfg/py.typed
ka_uts_cfg/setup.py
ka_uts_cfg/task.py
ka_uts_cfg-4.0.2.250518.dist-info/licenses/LICENSE.txt
ka_uts_cfg-4.0.2.250518.dist-info/METADATA
ka_uts_cfg-4.0.2.250518.dist-info/WHEEL
ka_uts_cfg-4.0.2.250518.dist-info/entry_points.txt
ka_uts_cfg-4.0.2.250518.dist-info/top_level.txt
ka_uts_cfg-4.0.2.250518.dist-info/RECORD
